{
    "combined_score": 0.6067728790296733,
    "public": {
        "macro_f1": 0.6068,
        "n_walks": 781,
        "f1_class0_normal": 0.7391,
        "f1_class1_mild": 0.5726,
        "f1_class2_severe": 0.5086,
        "per_fold_f1": {
            "1": {
                "macro_f1": 0.4405,
                "n_test_walks": 159,
                "n_train_walks": 622
            },
            "2": {
                "macro_f1": 0.5978,
                "n_test_walks": 122,
                "n_train_walks": 659
            },
            "3": {
                "macro_f1": 0.5491,
                "n_test_walks": 143,
                "n_train_walks": 638
            },
            "4": {
                "macro_f1": 0.6803,
                "n_test_walks": 115,
                "n_train_walks": 666
            },
            "5": {
                "macro_f1": 0.3876,
                "n_test_walks": 135,
                "n_train_walks": 646
            },
            "6": {
                "macro_f1": 0.4805,
                "n_test_walks": 107,
                "n_train_walks": 674
            }
        },
        "confusion_matrix": [
            [
                289,
                39,
                13
            ],
            [
                96,
                140,
                40
            ],
            [
                56,
                34,
                74
            ]
        ],
        "label_dist": {
            "1": 276,
            "0": 341,
            "2": 164
        },
        "pred_dist": {
            "0": 441,
            "1": 213,
            "2": 127
        },
        "mpjpe_mm": "N/A",
        "eval_time_s": 1217.46
    }
}